tratools/__init__.py
tratools/progress/__init__.py
tratools/progress/progress_cmd.py
tratools/progress/progress_main.py
tratools/progress/progress_notebook.py
tratools/scheduler/__init__.py
tratools/scheduler/scheduler.py
tratools/zipper/__init__.py
tratools/zipper/zipper.py
tratools-0.0.4.dev0.dist-info/LICENSE
tratools-0.0.4.dev0.dist-info/METADATA
tratools-0.0.4.dev0.dist-info/WHEEL
tratools-0.0.4.dev0.dist-info/top_level.txt
tratools-0.0.4.dev0.dist-info/RECORD
