Metadata-Version: 2.1
Name: tratools
Version: 0.0.4.dev0
Summary: some helpful tools
Home-page: https://github.com/tokentranslator-group/tratools
Author: tra-group
Author-email: 
License: UNKNOWN
Platform: UNKNOWN
Requires-Dist: pulp (==2.0)
Requires-Dist: pyschedule (>=0.2.34)
Requires-Dist: pandas (>=1.1.5)
Requires-Dist: numpy (>=1.18.5)
Requires-Dist: matplotlib
